{"api_core.md":"zlWMY--X","api_cross-tab.md":"AKH1N2C1","api_history.md":"CoWHRjH4","api_iframe.md":"ahXGbnY2","api_types.md":"w11ifIf-","examples_basic.md":"C7pht3gY","examples_cross-tab.md":"B0_rRwIl","examples_history.md":"CF5FJ7gv","examples_iframe.md":"BgDDRY7l","examples_patterns.md":"8OhEOv1T","examples_schema.md":"Ba_Tjaiu","guide_adapters_cross-tab.md":"BtAZlBK9","guide_adapters_history.md":"01BGbVqQ","guide_adapters_iframe.md":"cnZaPT_3","guide_advanced_best-practices.md":"CzfQOV1R","guide_advanced_performance.md":"ClzokE4A","guide_advanced_transports.md":"BbaQshSD","guide_advanced_troubleshooting.md":"rmvJ6s9O","guide_core-concepts.md":"DYuIipYN","guide_getting-started.md":"Dk0lmhOk","guide_handler-isolation.md":"DbhlmiuP","guide_installation.md":"BH24XBzm","guide_pub-sub.md":"D6p5NANs","guide_schema-validation.md":"DcDrbvsn","guide_source-filtering.md":"DM8PPrb7","guide_topic-patterns.md":"C9k-MXuL","index.md":"COTAJqSI","integrations_devtools.md":"CTKTMhd4","readme.md":"DxazYkjy"}
